<?xml version="1.0" encoding="UTF-8"?>
<objects serializationModel="Studio.01.07.00">
    <object class="AudioFile" id="{ddc7bde4-eab6-484a-823a-30dbb97a7088}">
        <property name="frequencyInKHz">
            <value>44.0999985</value>
        </property>
        <property name="channelCount">
            <value>2</value>
        </property>
        <property name="length">
            <value>242.5469387755102</value>
        </property>
        <property name="audioFilePath">
            <value>$(AUDIO_BIN_DIR)/Voice III (3) {fbdd7033-111d-4f2f-af32-b372b62ca179}.mp3</value>
        </property>
        <relationship name="container">
            <destination>{b62342fb-7e92-41e4-a677-3fc59bac55b4}</destination>
        </relationship>
    </object>
</objects>
